pytxt2morse/__init__.py
pytxt2morse/pytxt2morse.py
pytxt2morse-0.1.0.dist-info/License
pytxt2morse-0.1.0.dist-info/METADATA
pytxt2morse-0.1.0.dist-info/WHEEL
pytxt2morse-0.1.0.dist-info/top_level.txt
pytxt2morse-0.1.0.dist-info/RECORD
