Metadata-Version: 2.1
Name: pytxt2morse
Version: 0.1.0
Summary: Convert text to Morse code and Morse code to text.
Author: Md. Ismiel Hossen Abir
Author-email: ismielabir1971@gmail.com
Classifier: Programming Language :: Python :: 3
Classifier: License :: OSI Approved :: MIT License
Classifier: Operating System :: OS Independent
Classifier: Intended Audience :: Developers
Classifier: Topic :: Utilities
Requires-Python: >=3.6
License-File: License
